test_mcp_server_ap25092201/__init__.py
test_mcp_server_ap25092201/media_handler.py
test_mcp_server_ap25092201/prompt_client.py
test_mcp_server_ap25092201/prompt_server.py
test_mcp_server_ap25092201-0.1.10.dist-info/METADATA
test_mcp_server_ap25092201-0.1.10.dist-info/WHEEL
test_mcp_server_ap25092201-0.1.10.dist-info/entry_points.txt
test_mcp_server_ap25092201-0.1.10.dist-info/licenses/LICENSE
test_mcp_server_ap25092201-0.1.10.dist-info/RECORD
