Metadata-Version: 2.4
Name: test-mcp-server-ap25092201
Version: 0.1.10
Summary: Test MCP Server with media handling and prompt capabilities for bootstrap testing
Project-URL: Homepage, https://github.com/apisani1/test-mcp-server-ap25092201
Project-URL: Repository, https://github.com/apisani1/test-mcp-server-ap25092201
Project-URL: Documentation, https://test-mcp-server-ap25092201.readthedocs.io/
Project-URL: Changelog, https://github.com/apisani1/test-mcp-server-ap25092201/releases
Project-URL: Issues, https://github.com/apisani1/test-mcp-server-ap25092201/issues
Author-email: Antonio Pisani <antonio.pisani@gmail.com>
License: MIT
License-File: LICENSE
Keywords: ai,assistant,bootstrap,mcp,media,prompts,server,testing
Classifier: Development Status :: 4 - Beta
Classifier: Intended Audience :: Developers
Classifier: License :: OSI Approved :: MIT License
Classifier: Operating System :: OS Independent
Classifier: Programming Language :: Python :: 3
Classifier: Programming Language :: Python :: 3.10
Classifier: Programming Language :: Python :: 3.11
Classifier: Programming Language :: Python :: 3.12
Classifier: Topic :: Scientific/Engineering :: Artificial Intelligence
Classifier: Topic :: Software Development :: Libraries :: Python Modules
Requires-Python: >=3.10
Requires-Dist: mcp[cli]>=1.14.1
Requires-Dist: pillow>=10.0.0
Provides-Extra: all
Requires-Dist: black>=25.1.0; extra == 'all'
Requires-Dist: doc8>=0.8.0; extra == 'all'
Requires-Dist: flake8-pyproject>=1.2.0; extra == 'all'
Requires-Dist: flake8>=7.1.0; extra == 'all'
Requires-Dist: ipykernel>=6.29.5; extra == 'all'
Requires-Dist: isort>=6.0.0; extra == 'all'
Requires-Dist: mypy>=1.15; extra == 'all'
Requires-Dist: myst-parser>=4.0.0; extra == 'all'
Requires-Dist: pylint>=3.3.0; extra == 'all'
Requires-Dist: pytest-asyncio>=0.21.0; extra == 'all'
Requires-Dist: pytest-cov>=6.1.0; extra == 'all'
Requires-Dist: pytest>=7.4.0; extra == 'all'
Requires-Dist: python-dotenv>=1.1.0; extra == 'all'
Requires-Dist: sphinx-autobuild>=2021.3.14; extra == 'all'
Requires-Dist: sphinx-copybutton>=0.5.2; extra == 'all'
Requires-Dist: sphinx-rtd-theme>=3.0.2; extra == 'all'
Requires-Dist: sphinx-sitemap>=2.6.0; extra == 'all'
Requires-Dist: sphinx-tabs>=3.4.7; extra == 'all'
Requires-Dist: sphinx>=8.1.3; extra == 'all'
Provides-Extra: dev
Requires-Dist: ipykernel>=6.29.5; extra == 'dev'
Requires-Dist: python-dotenv>=1.1.0; extra == 'dev'
Provides-Extra: docs
Requires-Dist: doc8>=0.8.0; extra == 'docs'
Requires-Dist: myst-parser>=4.0.0; extra == 'docs'
Requires-Dist: sphinx-autobuild>=2021.3.14; extra == 'docs'
Requires-Dist: sphinx-copybutton>=0.5.2; extra == 'docs'
Requires-Dist: sphinx-rtd-theme>=3.0.2; extra == 'docs'
Requires-Dist: sphinx-sitemap>=2.6.0; extra == 'docs'
Requires-Dist: sphinx-tabs>=3.4.7; extra == 'docs'
Requires-Dist: sphinx>=8.1.3; extra == 'docs'
Provides-Extra: lint
Requires-Dist: black>=25.1.0; extra == 'lint'
Requires-Dist: flake8-pyproject>=1.2.0; extra == 'lint'
Requires-Dist: flake8>=7.1.0; extra == 'lint'
Requires-Dist: isort>=6.0.0; extra == 'lint'
Requires-Dist: pylint>=3.3.0; extra == 'lint'
Provides-Extra: test
Requires-Dist: pytest-asyncio>=0.21.0; extra == 'test'
Requires-Dist: pytest-cov>=6.1.0; extra == 'test'
Requires-Dist: pytest>=7.4.0; extra == 'test'
Provides-Extra: typing
Requires-Dist: mypy>=1.15; extra == 'typing'
